[{"username": "alstoncm", "url": "https://www.reddit.com/gallery/17qnwyn", "time": 1699456848.0, "subreddit": "r/ThePPShow", "title": "BBBY showing on Robinhood", "text": "<!-- SC_OFF --><div class=\"md\"><p>I was casually looking at BYON on robinhood and noticed an article was posted w/ BBBY mentioned &amp; to my surprise, it brings you to the ticker! What\u2019s weird though is that you can\u2019t search for BBBY or BBBYq but for some reason you can access the ticker through news links.</p>\n</div><!-- SC_ON -->", "preview": "<div class=\"img_container\"><img class=\"card-image\" src=\"https://b.thumbs.redditmedia.com/jb6J4TqrlOJyfJNybgkwGJzFWCrpY-dz90RTSNPPeNU.jpg\"/></div>"},
{"username": "alstoncm", "url": "https://i.redd.it/xn4sj9w9eqlb1.jpg", "time": 1693612092.0, "subreddit": "r/ThePPShow", "title": "ThePPShow x Pulte Charity Poker Event.", "text": "<!-- SC_OFF --><div class=\"md\"><p>Who\u2019s down for a charity poker event hosted by PP &amp; Pulte?</p>\n</div><!-- SC_ON -->", "preview": "<div class=\"img_container\"><img class=\"card-image\" src=\"https://i.redd.it/xn4sj9w9eqlb1.jpg\"/></div>"},
{"username": "alstoncm", "url": "https://i.redd.it/ihb6tgxrg42b1.jpg", "time": 1685065468.0, "subreddit": "r/ThePPShow", "title": "PETE THE SHILL\u2026 how did that IEP purchase go for you instead of buying bbbyq?", "text": null, "preview": "<div class=\"img_container\"><img class=\"card-image\" src=\"https://i.redd.it/ihb6tgxrg42b1.jpg\"/></div>"},
{"username": "alstoncm", "url": "https://i.redd.it/wv0e9qe36vza1.jpg", "time": 1684081218.0, "subreddit": "r/ThePPShow", "title": "Everything You Need To Know About Shill The Pilot.", "text": "<!-- SC_OFF --><div class=\"md\"><p>[removed]</p>\n</div><!-- SC_ON -->", "preview": "<div class=\"img_container\"><img class=\"card-image\" src=\"https://i.redd.it/wv0e9qe36vza1.jpg\"/></div>"}]