[{"username": "amasangkay", "url": "https://www.reddit.com/r/ThePPShow/comments/16f5hei/the_birth_of_teddy_due_date_after_combined/", "time": 1694365458.0, "subreddit": "r/ThePPShow", "title": "THE BIRTH OF $TEDDY, DUE DATE AFTER COMBINED HEARING ON SEPTEMBER 12, 2023", "text": "<!-- SC_OFF --><div class=\"md\"><p>[removed]</p>\n</div><!-- SC_ON -->", "flair": {"text": "Speculation/Opinion", "text_color": "dark", "back_color": "#ffd635"}, "preview": "<div class=\"img_container\"><img class=\"card-image\" src=\"https://b.thumbs.redditmedia.com/wDqXfUgy6MslCwvzHokWIq3wS2ffKprEgEctEAbSiLA.jpg\"/></div>"},
{"username": "amasangkay", "url": "https://www.reddit.com/r/ThePPShow/comments/16f13oc/the_birth_of_teddy_due_date_after_combined/", "time": 1694354649.0, "subreddit": "r/ThePPShow", "title": "THE BIRTH OF $TEDDY, DUE DATE AFTER COMBINED HEARING ON SEPTEMBER 12, 2023 -\u26a1eyxar@getalby.com \u26a1", "text": "<!-- SC_OFF --><div class=\"md\"><p>[removed]</p>\n</div><!-- SC_ON -->", "flair": {"text": "Speculation/Opinion", "text_color": "dark", "back_color": "#ffd635"}, "preview": "<div class=\"img_container\"><img class=\"card-image\" src=\"spoiler\"/></div>"}]