[{"username": "BednaR1", "url": "https://www.reddit.com/r/ThePPShow/comments/175m816/could_someone_make_a_nice_avengers_assemble_video/", "time": 1697051598.0, "subreddit": "r/ThePPShow", "title": "Could someone make a nice avengers assemble video, pretty please?", "text": null, "preview": "<div class=\"img_container\"><img class=\"card-image\" src=\"self\"/></div>"},
{"username": "BednaR1", "url": "https://i.redd.it/poloh31a2grb1.jpg", "time": 1696102076.0, "subreddit": "r/ThePPShow", "title": "No context", "text": null, "preview": "<div class=\"img_container\"><img class=\"card-image\" src=\"https://i.redd.it/poloh31a2grb1.jpg\"/></div>"}]