[{"username": "DaWeeFellaFellJesus", "url": "https://www.reddit.com/r/ThePPShow/comments/17erc2y/could_people_please_lay_off_with_all_the_customer/", "time": 1698085630.0, "subreddit": "r/ThePPShow", "title": "Could people please lay off with all the customer service agent posts. These people are there to help online purchasers, and not oracles of what the upper management are doing.", "text": "<!-- SC_OFF --><div class=\"md\"><p>Guys, these customer service people are there to help people with online purchases and issues.  </p>\n\n<p>The more you are bothering them with shit like this, means someone else is waiting for help, that actually might be buying something and having issues.  </p>\n\n<p>Wasting their time with questions like these posted today, might mean people that are waiting for help will just go.. .&quot;F it... I&#39;ll get it on Amazon.&quot;  How long do most of us wait for &quot;online help&quot; before going to Amazon or elsewhere on other purchases.</p>\n\n<p>And in turn, losing the business money, and surely that&#39;s a thing that people don&#39;t want, in the event we are issued shares in whatever comes next.</p>\n</div><!-- SC_ON -->", "preview": "<div class=\"img_container\"><img class=\"card-image\" src=\"self\"/></div>"}]