[{"username": "Disastrous_Ad_6613", "url": "https://i.redd.it/nhhhhy0nl4hb1.jpg", "time": 1691604825.0, "subreddit": "r/ThePPShow", "title": "Hard-to-Borrow Asset", "text": "<!-- SC_OFF --><div class=\"md\"><p>Just got this email from eTORO UK . I certainly do NOT have any short position in the stock - xxxx shares and counting BABYY \ud83d\ude80\ud83d\ude80\ud83d\ude80 HODL that shit</p>\n</div><!-- SC_ON -->", "flair": {"text": "SO YOU'RE TELLING ME THERE'S A CHANCE", "text_color": "dark", "back_color": "#94e044"}, "preview": "<div class=\"img_container\"><img class=\"card-image\" src=\"https://i.redd.it/nhhhhy0nl4hb1.jpg\"/></div>"}]