[{"username": "Envolution", "url": "https://twitter.com/ryancohen/status/1674573778196758528?s=46&amp;t=nOPBbpiKX7W0ruDEeUuUnQ", "time": 1688084600.0, "subreddit": "r/ThePPShow", "title": "Ryan Cohen on twitter.", "text": null, "flair": {"text": "Memes :d", "text_color": "dark", "back_color": "#7193ff"}, "preview": "<div class=\"img_container\"><img class=\"card-image\" src=\"default\"/></div>"},
{"username": "Envolution", "url": "https://twitter.com/ryancohen/status/1674573778196758528?s=46&amp;t=nOPBbpiKX7W0ruDEeUuUnQ", "time": 1688084600, "subreddit": "r/ThePPShow", "title": "Ryan Cohen on twitter.", "text": "", "flair": {"text": "Memes :d", "text_color": "dark", "back_color": "#7193ff"}, "preview": "<div class=\"img_container\"><img class=\"card-image\" src=\"https://b.thumbs.redditmedia.com/6qw6bkbLZtfGvWTxBsJdxpf6-xlIqQVJk3DGcX2C30U.jpg\"/></div>"},
{"username": "Envolution", "url": "https://twitter.com/ryancohen/status/1673915702842130433?s=46&amp;t=OQxY_9fsW8JhIpr7R8Gr3w", "time": 1687928307.0, "subreddit": "r/ThePPShow", "title": "Ryan Cohen on twitter", "text": null, "flair": {"text": "Memes :d", "text_color": "dark", "back_color": "#7193ff"}, "preview": "<div class=\"img_container\"><img class=\"card-image\" src=\"https://b.thumbs.redditmedia.com/tNiQ_yJCRZ7Xc7Ctb705_DWT8P9H-9-QLzeMd4e83zs.jpg\"/></div>"}]