[{"username": "ICUTOOO", "url": "https://i.redd.it/mqizzr8kgodb1.jpg", "time": 1690102058.0, "subreddit": "r/ThePPShow", "title": "KROLL DOWN FOR MAINTENANCE. MAYBE TRYING TO GET READY FOR THE MILLIONS OF APE'S PRESSING F5 WHEN THE ROCKET LAUNCHES TOMORROW\ud83d\ude80\ud83d\ude80\ud83d\ude80\ud83c\udff4\u200d\u2620\ufe0f\ud83c\udff4\u200d\u2620\ufe0f\ud83c\udff4\u200d\u2620\ufe0f", "text": null, "preview": "<div class=\"img_container\"><img class=\"card-image\" src=\"https://i.redd.it/mqizzr8kgodb1.jpg\"/></div>"}]