[{"username": "kidrich305", "url": "https://i.redd.it/rrtoychdg7ub1.jpg", "time": 1697305399.0, "subreddit": "r/ThePPShow", "title": "Get your fuckin space suits ready we\u2019re going to the fuckin moon \ud83d\ude80\ud83c\udf15\ud83d\udcb0\ud83d\ude0e\ud83e\uddf8\ud83e\udd8b\ud83d\udcaf", "text": null, "flair": {"text": "Memes :d", "text_color": "dark", "back_color": "#7193ff"}, "preview": "<div class=\"img_container\"><img class=\"card-image\" src=\"https://i.redd.it/rrtoychdg7ub1.jpg\"/></div>"},
{"username": "kidrich305", "url": "https://www.reddit.com/r/ThePPShow/comments/177usrd/get_your_fuckin_space_suits_ready_we_goin_to_the/", "time": 1697305231.0, "subreddit": "r/ThePPShow", "title": "Get your fuckin space suits ready we goin to the fuckin moon \ud83d\ude80\ud83c\udf15\ud83d\udcb0\ud83d\ude0e\ud83e\uddf8\ud83e\udd8b\ud83d\udcaf", "text": null, "flair": {"text": "Memes :d", "text_color": "dark", "back_color": "#7193ff"}, "preview": "<div class=\"img_container\"><img class=\"card-image\" src=\"self\"/></div>"},
{"username": "kidrich305", "url": "https://www.reddit.com/r/ThePPShow/comments/16s64rd/c8_corvette_coming_soonwhat_will_be_your_dream/", "time": 1695681016.0, "subreddit": "r/ThePPShow", "title": "C8 corvette coming soon\u203c\ufe0fwhat will be your dream car when we moon???\ud83d\ude80\ud83c\udf15\ud83d\udcb0\ud83d\ude0e", "text": null, "flair": {"text": "Stream announcement ", "text_color": "dark", "back_color": "#ffd635"}, "preview": "<div class=\"img_container\"><img class=\"card-image\" src=\"self\"/></div>"},
{"username": "kidrich305", "url": "https://www.reddit.com/r/ThePPShow/comments/16qcqlt/741_a_share_sounds_about_right/", "time": 1695496629.0, "subreddit": "r/ThePPShow", "title": "$741 a share sounds about right \ud83d\ude80\ud83d\ude80\ud83d\ude80\ud83d\ude80\ud83d\ude80\ud83d\ude80\ud83d\ude80\ud83d\ude80\ud83d\ude80\ud83d\ude80\ud83d\ude80\ud83d\ude80\ud83d\ude80\ud83d\ude80\ud83d\ude80\ud83d\ude80\ud83d\ude80\ud83d\ude80\ud83d\ude80\ud83d\ude80\ud83d\ude80\ud83d\ude80\ud83d\ude80\ud83d\ude80\ud83d\ude80\ud83c\udf15", "text": null, "flair": {"text": "BLACK TAR TINFOIL", "text_color": "dark", "back_color": "#ff66ac"}, "preview": "<div class=\"img_container\"><img class=\"card-image\" src=\"self\"/></div>"},
{"username": "kidrich305", "url": "https://www.reddit.com/r/ThePPShow/comments/16qckya/this_was_so_satisfying_thank_you_kais_you_are_the/", "time": 1695496229.0, "subreddit": "r/ThePPShow", "title": "This was so satisfying thank you Kais you are the true Bbbyq Legend https://x.com/kaismaalej/status/1705623469386309955?s=46", "text": null, "flair": {"text": "Stream announcement ", "text_color": "dark", "back_color": "#ffd635"}, "preview": "<div class=\"img_container\"><img class=\"card-image\" src=\"self\"/></div>"}]