[{"username": "KRAZYW0RLD", "url": "https://i.redd.it/ncroga6bm3qb1.png", "time": 1695515633.0, "subreddit": "r/ThePPShow", "title": "Fragile little SS mod banned me for this. What will I ever do?! /s", "text": null, "flair": {"text": "IM IN A GLASS CASE OF EMOTION", "text_color": "dark", "back_color": "#ff4500"}, "preview": "<div class=\"img_container\"><img class=\"card-image\" src=\"https://i.redd.it/ncroga6bm3qb1.png\"/></div>"},
{"username": "KRAZYW0RLD", "url": "https://www.reddit.com/r/ThePPShow/comments/16nvf0e/in_relation_to_ast_discussion_aka_fud_lets_not/", "time": 1695241334.0, "subreddit": "r/ThePPShow", "title": "In relation to AST \"discussion\" (aka fud), let's not forget Fidelity and Schwab are literally business partners with Citidel and Virtu.", "text": "<!-- SC_OFF --><div class=\"md\"><p>[removed]</p>\n</div><!-- SC_ON -->", "flair": {"text": "IM IN A GLASS CASE OF EMOTION", "text_color": "dark", "back_color": "#ff4500"}, "preview": "<div class=\"img_container\"><img class=\"card-image\" src=\"self\"/></div>"},
{"username": "KRAZYW0RLD", "url": "https://www.reddit.com/gallery/16lc9tz", "time": 1694985006.0, "subreddit": "r/ThePPShow", "title": "For those declaring FUDelity as the most trustworthy broker. How soon we forget, when in 201 they partnered with Citadel and Virtu. CEO ostrich Abby Johnson made 6+ B-B-Billion directly from you and is not your friend.", "text": null, "flair": {"text": "IM IN A GLASS CASE OF EMOTION", "text_color": "dark", "back_color": "#ff4500"}, "preview": "<div class=\"img_container\"><img class=\"card-image\" src=\"https://b.thumbs.redditmedia.com/-joDsLaFKzFrGeoqkvABShc52_eyec86iGsfRIjtPIA.jpg\"/></div>"}]