[{"username": "MarkTib1109", "url": "https://www.reddit.com/r/ThePPShow/comments/17sxnb7/hbc_counter_to_holdings_correct_me_if_im_wrong/", "time": 1699719131.0, "subreddit": "r/ThePPShow", "title": "HBC counter to % holdings. Correct me if I\u2019m wrong", "text": "<!-- SC_OFF --><div class=\"md\"><p>Looking through the posts this morning there was a very noticeable post about Fintel retail ownership. The math was completely wrong, but yet it\u2019s still up. The biggest battle to date is the amount of information we get and what we get needs to be true. This made me think about the big debate over HBC and I did some math and here is what I see. Let\u2019s use round numbers. </p>\n\n<p>TSO 739M\nHBC last holding 24M</p>\n\n<p>4.5% = 33M\n3.3% = 24M</p>\n\n<p>If this is wrong I will gladly delete, just want the right info for the thesis behind HBC being correct and then not being allowed to sell.</p>\n</div><!-- SC_ON -->", "preview": "<div class=\"img_container\"><img class=\"card-image\" src=\"self\"/></div>"},
{"username": "MarkTib1109", "url": "https://www.reddit.com/r/ThePPShow/comments/17n7zk5/need_opinions_on_the_board_support/", "time": 1699053463.0, "subreddit": "r/ThePPShow", "title": "Need opinions on the board support.", "text": "<!-- SC_OFF --><div class=\"md\"><p>I\u2019ve been in this play for a long time now going on two years and the one thing that has never set right with me is understanding the support for the board. Just trying to get some feedback as to why anyone supported the board until the very end.</p>\n</div><!-- SC_ON -->", "preview": "<div class=\"img_container\"><img class=\"card-image\" src=\"self\"/></div>"},
{"username": "MarkTib1109", "url": "https://i.redd.it/2m5ft9adeswb1.jpg", "time": 1698430665.0, "subreddit": "r/ThePPShow", "title": "Paging u/BiggySmallzzz", "text": "<!-- SC_OFF --><div class=\"md\"><p>Biggy does this hold weight? Credit to OP on Twitter.</p>\n</div><!-- SC_ON -->", "preview": "<div class=\"img_container\"><img class=\"card-image\" src=\"https://i.redd.it/2m5ft9adeswb1.jpg\"/></div>"},
{"username": "MarkTib1109", "url": "https://www.reddit.com/r/ThePPShow/comments/16jcdnx/why_0_premarket/", "time": 1694781839.0, "subreddit": "r/ThePPShow", "title": "Why 0 premarket?", "text": "<!-- SC_OFF --><div class=\"md\"><p>Can anyone see any premarket movement, we have had it up until today?</p>\n</div><!-- SC_ON -->", "preview": "<div class=\"img_container\"><img class=\"card-image\" src=\"self\"/></div>"},
{"username": "MarkTib1109", "url": "https://x.com/phantomblack691/status/1694833940903637024?s=46&amp;t=HPC0AlVqJdiqWAm5oW7Vkw", "time": 1693194561.0, "subreddit": "r/ThePPShow", "title": "This is a must listen\u2026 it\u2019s long, but is absolutely full of great info. David is a beast!", "text": null, "preview": "<div class=\"img_container\"><img class=\"card-image\" src=\"https://b.thumbs.redditmedia.com/UqUUzu5mpRYJTQ3TgQgf6PAT7OOWlhAANB162RAc12Y.jpg\"/></div>"},
{"username": "MarkTib1109", "url": "https://i.redd.it/7xjzti1f4pjb1.jpg", "time": 1692726861, "subreddit": "r/ThePPShow", "title": "Why are we still here bro?", "text": "", "preview": "<div class=\"img_container\"><img class=\"card-image\" src=\"https://i.redd.it/7xjzti1f4pjb1.jpg\"/></div>"},
{"username": "MarkTib1109", "url": "https://i.redd.it/bfr46exj0jhb1.jpg", "time": 1691779358.0, "subreddit": "r/ThePPShow", "title": "David Simpson gone now??", "text": null, "preview": "<div class=\"img_container\"><img class=\"card-image\" src=\"https://i.redd.it/bfr46exj0jhb1.jpg\"/></div>"},
{"username": "MarkTib1109", "url": "https://i.redd.it/wz0agslilddb1.jpg", "time": 1689970351.0, "subreddit": "r/ThePPShow", "title": "Wen vote?? Deadline for votes 9/1/23. Hearing 9/7/23. Let\u2019s do this!!", "text": null, "preview": "<div class=\"img_container\"><img class=\"card-image\" src=\"https://i.redd.it/wz0agslilddb1.jpg\"/></div>"},
{"username": "MarkTib1109", "url": "https://i.redd.it/uszho4g47y8b1.jpg", "time": 1688040545.0, "subreddit": "r/ThePPShow", "title": "We knew it was coming, dip before rip!!", "text": null, "preview": "<div class=\"img_container\"><img class=\"card-image\" src=\"https://i.redd.it/uszho4g47y8b1.jpg\"/></div>"},
{"username": "MarkTib1109", "url": "https://i.redd.it/sq5538h35s7b1.jpg", "time": 1687531401.0, "subreddit": "r/ThePPShow", "title": "Let\u2019s go! Steady we go.", "text": null, "preview": "<div class=\"img_container\"><img class=\"card-image\" src=\"https://i.redd.it/sq5538h35s7b1.jpg\"/></div>"}]