[{"username": "Ok-Information-6722", "url": "https://www.reddit.com/r/ThePPShow/comments/173b407/all_the_references_to_china_from_rceo_refer_to/", "time": 1696802098.0, "subreddit": "r/ThePPShow", "title": "All the references to China from RCEO refer to Loopring", "text": "<!-- SC_OFF --><div class=\"md\"><p>A sleeping giant, with a patent for a decentralized exchange that prevent frontrunning with this thing they called AMM Pool. </p>\n\n<p>AMM stands for Automated Market Maker.</p>\n\n<p>It runs on Layer 2 with ridiculous low transaction fees, and instant settlement.</p>\n\n<p>GME NFT marketplace is built on Loopring.</p>\n\n<p>GME wallet too.</p>\n\n<p>Loopring kept polishing their UI and implemented features that remove frictiin for adoption, like the ability for a user to cover the wallet creation fee for its customers.</p>\n\n<p>Imagine a product where users don&#39;t need any knowledge about crypto or blockchain, but still can experience web3.</p>\n\n<p>Comes PLAYR.</p>\n\n<p>A web3 launcher, maybe more like a decentralized exchange, where games and stocks can be bought and owned in the blockchain. No middleman.</p>\n\n<p>The GME wallet is not to be discontinued, it could be transferred to a bank entity. Like Teddy.</p>\n\n<p>GME delists from the NYSE. TEDDY operates as the new exchange, running on Loopring.</p>\n\n<p>Be your own bank.</p>\n</div><!-- SC_ON -->", "preview": "<div class=\"img_container\"><img class=\"card-image\" src=\"self\"/></div>"}]