[{"username": "Old_Forever_6220", "url": "https://www.reddit.com/r/ThePPShow/comments/17genka/my_pp_is_growing/", "time": 1698266829.0, "subreddit": "r/ThePPShow", "title": "My PP is growing", "text": "<!-- SC_OFF --><div class=\"md\"><p><a href=\"https://twitter.com/BedBathBeyond/status/1717278639555793096?t=q7n-rMyddBzDnonGnr4wjg&amp;s=19\">https://twitter.com/BedBathBeyond/status/1717278639555793096?t=q7n-rMyddBzDnonGnr4wjg&amp;s=19</a></p>\n\n<p>Probably nothing. Hopefully something</p>\n</div><!-- SC_ON -->", "flair": {"text": "BLACK TAR TINFOIL", "text_color": "dark", "back_color": "#ff66ac"}, "preview": "<div class=\"img_container\"><img class=\"card-image\" src=\"self\"/></div>"}]