[{"username": "Overall_Building_407", "url": "https://www.reddit.com/r/ThePPShow/comments/1458dt3/speculation_minimum_7_bid_and_could_be_as_high_as/", "time": 1686324760.0, "subreddit": "r/ThePPShow", "title": "SPECULATION: MINIMUM $7 BID AND COULD BE AS HIGH AS $35 PAID AS SPECIAL DIVIDEND + 1 STOCK UNIT(1:100 IEP, 1:100 GME + 1:2 TEDDY) PER EACH BBBYQ SHARE HELD. WHAT\u2019S YOUR OPINION REGARDING A REASONABLE EXPECTED BID FOR BED BATH &amp; BEYOND INCLUDING BABY? LET ME JNOW IN COMMENTS", "text": "<!-- SC_OFF --><div class=\"md\"><p>MY OPINION &amp; SUPER TINFOIL(NOT FINANCIAL ADVIC):  </p>\n\n<p>$5-$10 PER SHARE CASH  PAID AS SPECIAL DIVIDEND </p>\n\n<p>+ 1 STOCk UNIT PER EVERY BBBYQ SHARE HELD</p>\n\n<p>STOCK UNIT = 1:100 IEP, 1:100 GME + 1:2 TEDDY</p>\n\n<p>REASON:</p>\n\n<p>BASED ON WHAT WAS DISCUSSED GME RAISES $2.8 B + IEP RAISES $2 B together which comes to $7 PER SHARE, THIS IS MINIMUM IMO, THEY COULD SURPRISE BY DOING $25 - $35 CASH as majority of this will get paid back to themselves</p>\n\n<p>ASSUMING ICHAN(DISGUISED) MOST LIKELY OWNS 311 MILLION SHARES WHICH HE\u2019LL TRANSFER TO IEP AND PAY IN STOCK UNITS</p>\n\n<p>RC VENTURES(DISGUISED) COULD BE OWNING 311 MILLION FLOAT AMONG A GROUP WITH EACH HOLDERS OWNING APPROX 4.5% OF BBBYQ FLOAT</p>\n</div><!-- SC_ON -->", "preview": "<div class=\"img_container\"><img class=\"card-image\" src=\"self\"/></div>"},
{"username": "Overall_Building_407", "url": "https://www.reddit.com/r/ThePPShow/comments/144gwbi/added_50k_more_shares_to_650k_position_need_to/", "time": 1686248691.0, "subreddit": "r/ThePPShow", "title": "ADDED 50K MORE SHARES TO 650K POSITION, NEED TO HEAR SOME POSITIVE THOUGHTS-GOING FOR A HERO OR ZERO, ARE WE CLOSE?", "text": "<!-- SC_OFF --><div class=\"md\"><p>HEARD DAVID SIMPSON AND IT HELPED MY CONVICTION</p>\n</div><!-- SC_ON -->", "preview": "<div class=\"img_container\"><img class=\"card-image\" src=\"self\"/></div>"}]