[{"username": "Peterslum", "url": "https://www.reddit.com/r/ThePPShow/comments/17k5xr7/fuck_you_another_1000_fuck_you/", "time": 1698705727.0, "subreddit": "r/ThePPShow", "title": "Fuck you\u2026 another 1000$ fuck you.", "text": "<!-- SC_OFF --><div class=\"md\"><p>Tired of this the lower it goes the more I buy bullshit. I buy at the bid not the ask. Have been ever since march 2021, yea I came late. I am a 45$ average pirate. I do not set my buying of share at the ask because simply if your not stupid, lowering the basis. I buy at market or even do orders at the high bid. Why you may ask? Because I\u2019m fucking stupid and find value in GameStop. Fuck all the\u2026. Oh I bought the dip. I buy the highest fucking bid. </p>\n\n<p>Need proof? I\u2019ll DM you. </p>\n\n<p>I buy high and always fuckin will. Why? I love the fucking stock</p>\n</div><!-- SC_ON -->", "flair": {"text": "MISLEADING", "text_color": "dark", "back_color": "#ea0027"}, "preview": "<div class=\"img_container\"><img class=\"card-image\" src=\"self\"/></div>"}]