[{"username": "PHILANTHROPOS81", "url": "https://i.redd.it/w11yyms9detb1.jpg", "time": 1696953255.0, "subreddit": "r/ThePPShow", "title": "TD Direct Investing Canada* Still showing my 20,000 shrs DRS accounts showing ZERO What the \ud83e\udd2c is going on??", "text": null, "preview": "<div class=\"img_container\"><img class=\"card-image\" src=\"https://i.redd.it/w11yyms9detb1.jpg\"/></div>"},
{"username": "PHILANTHROPOS81", "url": "/r/Superstonk/comments/16cgmb9/proof_gamestop_is_gearing_up_for_ma_activity_per/", "time": 1695210094.0, "subreddit": "r/ThePPShow", "title": "An Oldie but a Goodie\ud83e\udef6 Proof Gamestop is gearing up for M&amp;A activity per their Credit Agreement, and how it fits into our collective thesis. Guess what? It's almost time.", "text": null, "preview": ""},
{"username": "PHILANTHROPOS81", "url": "https://i.redd.it/ipgxmp4bm94b1.jpg", "time": 1685999560.0, "subreddit": "r/ThePPShow", "title": "Mingle with Billionaire Philanthropists, so when the time comes they could be your biggest donors, for the REAL 100% non profit Charity. \ud83e\udd14#MegaPowersBack Can you dig it!!! @pulte @ryancohen #Pulte #RC $BBBY #BBBY #BBBYQ #BuyBuyBaby #BedBathAndBeyond #HulkHogan #MachoMan #WWF", "text": null, "preview": "<div class=\"img_container\"><img class=\"card-image\" src=\"https://i.redd.it/ipgxmp4bm94b1.jpg\"/></div>"}]