[{"username": "RepresentativeFee579", "url": "https://www.reddit.com/r/ThePPShow/comments/17q077z/gamestopteddy_speculation_what_if_pro_membership/", "time": 1699379996.0, "subreddit": "r/ThePPShow", "title": "GameStop/Teddy Speculation: what if pro membership turns into prime membership competitor", "text": "<!-- SC_OFF --><div class=\"md\"><p>What if GameStop\u2019s Playr gives pro members access to cloud NFT gaming as well as discounts on physical purchases.  Could GameStop be a part of the Amazon &amp; Amazon Prime behemoth competitor?</p>\n</div><!-- SC_ON -->", "preview": "<div class=\"img_container\"><img class=\"card-image\" src=\"self\"/></div>"},
{"username": "RepresentativeFee579", "url": "https://www.reddit.com/gallery/17nwjfu", "time": 1699134687.0, "subreddit": "r/ThePPShow", "title": "Pulte liked my joking twitter reply about having 7 kids", "text": "<!-- SC_OFF --><div class=\"md\"><p>I responded to Pulte\u2019s tweet from a day ago about having more kids and Pulte came back to like it.  Is BBBY giving us 7 kids?  I hope so.</p>\n</div><!-- SC_ON -->", "preview": "<div class=\"img_container\"><img class=\"card-image\" src=\"https://b.thumbs.redditmedia.com/ToePSSKrlosiGUkJujfm2QSvylvfJZTlHNXEgYLQaEE.jpg\"/></div>"},
{"username": "RepresentativeFee579", "url": "https://i.redd.it/88p8z8afmqwb1.jpg", "time": 1698409165.0, "subreddit": "r/ThePPShow", "title": "Happy 165th birthday, Teddy!", "text": null, "preview": "<div class=\"img_container\"><img class=\"card-image\" src=\"https://i.redd.it/88p8z8afmqwb1.jpg\"/></div>"}]