[{"username": "stong83", "url": "https://i.redd.it/w06v5sb1f60c1.png", "time": 1699907970.0, "subreddit": "r/ThePPShow", "title": "Tomorrow's hearing cancelled? Copied from Kroll site.", "text": null, "flair": {"text": "\ud83e\udd26\u200d\u2642\ufe0f Out of the loop. \ud83d\udca9 ", "text_color": "dark", "back_color": "#a06324"}, "preview": "<div class=\"img_container\"><img class=\"card-image\" src=\"https://i.redd.it/w06v5sb1f60c1.png\"/></div>"},
{"username": "stong83", "url": "https://www.reddit.com/r/ThePPShow/comments/176btkk/t_minus_1_hour/", "time": 1697130053.0, "subreddit": "r/ThePPShow", "title": "T minus 1 hour", "text": null, "flair": {"text": "TRUST ME BRO", "text_color": "dark", "back_color": "#ea0027"}, "preview": "<div class=\"img_container\"><img class=\"card-image\" src=\"self\"/></div>"},
{"username": "stong83", "url": "https://www.reddit.com/r/ThePPShow/comments/176bstr/t_minus_1_hour/", "time": 1697130009.0, "subreddit": "r/ThePPShow", "title": "T minus 1 hour", "text": null, "flair": {"text": "TRUST ME BRO", "text_color": "dark", "back_color": "#ea0027"}, "preview": "<div class=\"img_container\"><img class=\"card-image\" src=\"self\"/></div>"}]