[{"username": "StrikingLiving3394", "url": "https://v.redd.it/uj42q6cg35wa1", "time": 1682458007.0, "subreddit": "r/ThePPShow", "title": "What happened. Wen live? Emergency meeting.", "text": "<!-- SC_OFF --><div class=\"md\"><p>[removed]</p>\n</div><!-- SC_ON -->", "preview": "<div class=\"img_container\"><img class=\"card-image\" src=\"default\"/></div>"},
{"username": "StrikingLiving3394", "url": "https://v.redd.it/uj42q6cg35wa1", "time": 1682458007, "subreddit": "r/ThePPShow", "title": "What happened. Wen live? Emergency meeting.", "text": "PPBleeds U-Wrong and ABankruptCy didn\u2019t wanna list but you got a whole load of bag holders. PP match the energy in this video after delisting please. ", "preview": "<div class=\"img_container\"><img class=\"card-image\" src=\"https://external-preview.redd.it/jPQCrhvegED9ZC8r9gRCe1_R-DGs6GmmvlIiJAWrSSA.png?width=140&amp;height=78&amp;crop=140:78,smart&amp;format=jpg&amp;v=enabled&amp;lthumb=true&amp;s=e70b7fa674956c8e2c9b03aae5913b2ff7fbbb85\"/></div>"}]