[{"username": "sweattpalms", "url": "https://www.reddit.com/gallery/17mvcbf", "time": 1699018813.0, "subreddit": "r/ThePPShow", "title": "Unusual bid/ask activity on GME", "text": "<!-- SC_OFF --><div class=\"md\"><p>[removed]</p>\n</div><!-- SC_ON -->", "flair": {"text": "Speculation/Opinion", "text_color": "dark", "back_color": "#ffd635"}, "preview": "<div class=\"img_container\"><img class=\"card-image\" src=\"https://a.thumbs.redditmedia.com/cta8ANEMHMRKo0t977V4FPBTZEa0w_Y_9ZeLzI7ycC4.jpg\"/></div>"}]