[{"username": "Upstairs_Hospital_94", "url": "https://i.redd.it/052lz7ex6frb1.jpg", "time": 1696091532.0, "subreddit": "r/ThePPShow", "title": "Feel bad for the person who sent me a \u201cReddit Cares\u201d", "text": null, "flair": {"text": "Memes :d", "text_color": "dark", "back_color": "#7193ff"}, "preview": "<div class=\"img_container\"><img class=\"card-image\" src=\"https://i.redd.it/052lz7ex6frb1.jpg\"/></div>"},
{"username": "Upstairs_Hospital_94", "url": "https://i.redd.it/7nvwdwxjyuza1.jpg", "time": 1684078692.0, "subreddit": "r/ThePPShow", "title": "You Can Get Banned from WSB for Watching the PPShow.", "text": null, "flair": {"text": "Memes :d", "text_color": "dark", "back_color": "#7193ff"}, "preview": "<div class=\"img_container\"><img class=\"card-image\" src=\"https://i.redd.it/7nvwdwxjyuza1.jpg\"/></div>"},
{"username": "Upstairs_Hospital_94", "url": "https://www.reddit.com/gallery/12x222y", "time": 1682308356.0, "subreddit": "r/ThePPShow", "title": "Icahn tell you one thing \ud83e\udd43\ud83d\udc68\u200d\ud83d\ude80", "text": null, "flair": {"text": "", "text_color": "", "back_color": ""}, "preview": "<div class=\"img_container\"><img class=\"card-image\" src=\"https://www.redditstatic.com/desktop2x/img/renderTimingPixel.png\"/></div>"}]